{
  "dataset_fingerprint": "5dbc591a5f3ac532378c92cce0a770e45464bdc9c46c0f44cc51767cbe0509b5",
  "generated_at": "2026-04-12T12:58:41.263268Z",
  "tables": {
    "khushi": {
      "name": "khushi",
      "file_path": "/Users/ishantmadaan/Projects/Natwest-talk_to_data/data/khushi.csv",
      "row_count": 24,
      "inferred_time_column": "date",
      "measures": [
        "revenue",
        "orders",
        "customers",
        "ad_spend",
        "returns"
      ],
      "dimensions": [
        "region",
        "product",
        "channel"
      ],
      "id_columns": [],
      "columns": {
        "date": {
          "name": "date",
          "inferred_type": "date",
          "missing_count": 0,
          "total_count": 24,
          "unique_count": 3,
          "min_value": null,
          "max_value": null,
          "sample_values": [
            "2024-01-01",
            "2024-02-01",
            "2024-03-01"
          ],
          "high_cardinality": false
        },
        "region": {
          "name": "region",
          "inferred_type": "categorical",
          "missing_count": 0,
          "total_count": 24,
          "unique_count": 4,
          "min_value": null,
          "max_value": null,
          "sample_values": [
            "North",
            "South",
            "East",
            "West"
          ],
          "high_cardinality": false
        },
        "product": {
          "name": "product",
          "inferred_type": "categorical",
          "missing_count": 0,
          "total_count": 24,
          "unique_count": 2,
          "min_value": null,
          "max_value": null,
          "sample_values": [
            "A",
            "B"
          ],
          "high_cardinality": false
        },
        "channel": {
          "name": "channel",
          "inferred_type": "categorical",
          "missing_count": 0,
          "total_count": 24,
          "unique_count": 2,
          "min_value": null,
          "max_value": null,
          "sample_values": [
            "Online",
            "Offline"
          ],
          "high_cardinality": false
        },
        "revenue": {
          "name": "revenue",
          "inferred_type": "numeric",
          "missing_count": 0,
          "total_count": 24,
          "unique_count": 15,
          "min_value": 6000.0,
          "max_value": 16000.0,
          "sample_values": [],
          "high_cardinality": false
        },
        "orders": {
          "name": "orders",
          "inferred_type": "numeric",
          "missing_count": 0,
          "total_count": 24,
          "unique_count": 13,
          "min_value": 120.0,
          "max_value": 280.0,
          "sample_values": [],
          "high_cardinality": false
        },
        "customers": {
          "name": "customers",
          "inferred_type": "numeric",
          "missing_count": 0,
          "total_count": 24,
          "unique_count": 13,
          "min_value": 100.0,
          "max_value": 250.0,
          "sample_values": [],
          "high_cardinality": false
        },
        "ad_spend": {
          "name": "ad_spend",
          "inferred_type": "numeric",
          "missing_count": 0,
          "total_count": 24,
          "unique_count": 15,
          "min_value": 1200.0,
          "max_value": 3200.0,
          "sample_values": [],
          "high_cardinality": false
        },
        "returns": {
          "name": "returns",
          "inferred_type": "numeric",
          "missing_count": 0,
          "total_count": 24,
          "unique_count": 15,
          "min_value": 9.0,
          "max_value": 26.0,
          "sample_values": [],
          "high_cardinality": false
        }
      }
    }
  },
  "notes": []
}